{"II": {"egg_moves": [], "regular_moves": []}, "III": {"egg_moves": [], "regular_moves": []}, "IV": {"egg_moves": [], "regular_moves": []}, "V": {"egg_moves": [], "regular_moves": []}, "VI": {"egg_moves": [], "regular_moves": []}, "VII": {"egg_moves": ["After You", "Amnesia*", "Endure*", "Lucky Chant", "After You", "Amnesia*", "Endure*", "Lucky Chant"], "regular_moves": [{"Name": "Helping Hand", "Level": "01"}, {"Name": "Vine Whip", "Level": "01"}, {"Name": "Flower Shield", "Level": "01"}, {"Name": "Leech Seed", "Level": "04"}, {"Name": "Draining Kiss", "Level": "07"}, {"Name": "Magical Leaf", "Level": "10"}, {"Name": "Growth", "Level": "13"}, {"Name": "Wrap", "Level": "16"}, {"Name": "Sweet Kiss", "Level": "19"}, {"Name": "Natural Gift", "Level": "22"}, {"Name": "Petal Blizzard", "Level": "25"}, {"Name": "Synthesis", "Level": "28"}, {"Name": "Sweet Scent", "Level": "31"}, {"Name": "Grass Knot", "Level": "34"}, {"Name": "Floral Healing", "Level": "37"}, {"Name": "Petal Dance", "Level": "40"}, {"Name": "Aromatherapy", "Level": "43"}, {"Name": "Grassy Terrain", "Level": "46"}, {"Name": "Play Rough", "Level": "49"}, {"Name": "Helping Hand", "Level": "01"}, {"Name": "Vine Whip", "Level": "01"}, {"Name": "Flower Shield", "Level": "01"}, {"Name": "Leech Seed", "Level": "04"}, {"Name": "Draining Kiss", "Level": "07"}, {"Name": "Magical Leaf", "Level": "10"}, {"Name": "Growth", "Level": "13"}, {"Name": "Wrap", "Level": "16"}, {"Name": "Sweet Kiss", "Level": "19"}, {"Name": "Natural Gift", "Level": "22"}, {"Name": "Petal Blizzard", "Level": "25"}, {"Name": "Synthesis", "Level": "28"}, {"Name": "Sweet Scent", "Level": "31"}, {"Name": "Grass Knot", "Level": "34"}, {"Name": "Floral Healing", "Level": "37"}, {"Name": "Petal Dance", "Level": "40"}, {"Name": "Aromatherapy", "Level": "43"}, {"Name": "Grassy Terrain", "Level": "46"}, {"Name": "Play Rough", "Level": "49"}]}}