{"II": {"egg_moves": ["Bite", "Disable", "Light Screen", "Reflect*", "Spite"], "regular_moves": [{"Name": "Tackle", "Level": "01"}, {"Name": "Leer", "Level": "08"}, {"Name": "Hypnosis", "Level": "15"}, {"Name": "Stomp", "Level": "23"}, {"Name": "SandAttack", "Level": "31"}, {"Name": "Take Down", "Level": "40"}, {"Name": "Confuse Ray", "Level": "49"}]}, "III": {"egg_moves": ["Bite", "Disable", "Extrasensory", "Psych Up", "Spite", "Swagger"], "regular_moves": [{"Name": "Tackle", "Level": "01"}, {"Name": "Leer", "Level": "07"}, {"Name": "Astonish", "Level": "11"}, {"Name": "Hypnosis", "Level": "17"}, {"Name": "Stomp", "Level": "21"}, {"Name": "SandAttack", "Level": "27"}, {"Name": "Role Play", "Level": "31"}, {"Name": "Take Down", "Level": "37"}, {"Name": "Confuse Ray", "Level": "41"}, {"Name": "Calm Mind", "Level": "47"}]}, "IV": {"egg_moves": ["Bite", "Disable", "Double Kick", "Extrasensory", "MegahornHGSS", "Psych Up", "Spite", "Swagger", "Thrash", "Zen Headbutt"], "regular_moves": [{"Name": "Tackle", "Level": "01"}, {"Name": "Leer", "Level": "03"}, {"Name": "Astonish", "Level": "07"}, {"Name": "Hypnosis", "Level": "10"}, {"Name": "Stomp", "Level": "13"}, {"Name": "SandAttack", "Level": "16"}, {"Name": "Take Down", "Level": "21"}, {"Name": "Confuse Ray", "Level": "23"}, {"Name": "Calm Mind", "Level": "27"}, {"Name": "Role Play", "Level": "33"}, {"Name": "Zen Headbutt", "Level": "38"}, {"Name": "Imprison", "Level": "43"}, {"Name": "Captivate", "Level": "49"}, {"Name": "Me First", "Level": "53"}]}, "V": {"egg_moves": ["Bite", "Disable", "Double Kick", "Extrasensory", "Megahorn", "Me First", "Mud Sport", "Rage", "Spite", "Thrash", "Zen Headbutt"], "regular_moves": [{"Name": "Tackle", "Level": "01"}, {"Name": "Leer", "Level": "03"}, {"Name": "Astonish", "Level": "07"}, {"Name": "Hypnosis", "Level": "10"}, {"Name": "Stomp", "Level": "13"}, {"Name": "SandAttack", "Level": "16"}, {"Name": "Take Down", "Level": "21"}, {"Name": "Confuse Ray", "Level": "23"}, {"Name": "Calm Mind", "Level": "27"}, {"Name": "Role Play", "Level": "33"}, {"Name": "Zen Headbutt", "Level": "38"}, {"Name": "Jump Kick", "Level": "43"}, {"Name": "Imprison", "Level": "49"}, {"Name": "Captivate", "Level": "53"}, {"Name": "Me First", "Level": "55"}]}, "VI": {"egg_moves": ["Bite", "Disable", "Double Kick", "Extrasensory", "Megahorn", "Me First", "Mud Sport", "Rage", "Spite", "Thrash", "Zen Headbutt"], "regular_moves": [{"Name": "Me First", "Level": "01"}, {"Name": "Tackle", "Level": "01"}, {"Name": "Leer", "Level": "03"}, {"Name": "Astonish", "Level": "07"}, {"Name": "Hypnosis", "Level": "10"}, {"Name": "Stomp", "Level": "13"}, {"Name": "Sand Attack", "Level": "16"}, {"Name": "Take Down", "Level": "21"}, {"Name": "Confuse Ray", "Level": "23"}, {"Name": "Calm Mind", "Level": "27"}, {"Name": "Role Play", "Level": "33"}, {"Name": "Zen Headbutt", "Level": "38"}, {"Name": "Jump Kick", "Level": "43"}, {"Name": "Imprison", "Level": "49"}, {"Name": "Captivate", "Level": "50"}, {"Name": "Me First", "Level": "55"}]}, "VII": {"egg_moves": ["Bite", "Disable", "Double Kick", "Extrasensory", "Me First", "Megahorn", "Mud Sport", "Rage", "Spite", "Thrash", "Zen Headbutt", "Bite", "Disable", "Double Kick", "Extrasensory", "Me First", "Megahorn", "Mud Sport", "Rage", "Spite", "Thrash", "Zen Headbutt"], "regular_moves": [{"Name": "Me First", "Level": "01"}, {"Name": "Tackle", "Level": "01"}, {"Name": "Leer", "Level": "03"}, {"Name": "Astonish", "Level": "07"}, {"Name": "Hypnosis", "Level": "10"}, {"Name": "Stomp", "Level": "13"}, {"Name": "Sand Attack", "Level": "16"}, {"Name": "Take Down", "Level": "21"}, {"Name": "Confuse Ray", "Level": "23"}, {"Name": "Calm Mind", "Level": "27"}, {"Name": "Role Play", "Level": "33"}, {"Name": "Zen Headbutt", "Level": "38"}, {"Name": "Jump Kick", "Level": "43"}, {"Name": "Imprison", "Level": "49"}, {"Name": "Captivate", "Level": "50"}, {"Name": "Me First", "Level": "55"}, {"Name": "Me First", "Level": "01"}, {"Name": "Tackle", "Level": "01"}, {"Name": "Leer", "Level": "03"}, {"Name": "Astonish", "Level": "07"}, {"Name": "Hypnosis", "Level": "10"}, {"Name": "Stomp", "Level": "13"}, {"Name": "Sand Attack", "Level": "16"}, {"Name": "Take Down", "Level": "21"}, {"Name": "Confuse Ray", "Level": "23"}, {"Name": "Calm Mind", "Level": "27"}, {"Name": "Role Play", "Level": "33"}, {"Name": "Zen Headbutt", "Level": "38"}, {"Name": "Jump Kick", "Level": "43"}, {"Name": "Imprison", "Level": "49"}, {"Name": "Captivate", "Level": "50"}, {"Name": "Me First", "Level": "55"}]}}